{"resourceType":"SearchParameter","id":"krcore-sp-encounter-class","text":{"status":"generated","div":"<div xmlns=\"http://www.w3.org/1999/xhtml\"><h2>KRCoreSearchParameterEncounterClass</h2><p>Parameter <code>class</code>:<code>token</code></p><div><p>진료 구분</p>\n</div><table class=\"grid\"><tr><td>Resource</td><td><a href=\"http://hl7.org/fhir/R4/encounter.html\">Encounter</a></td></tr><tr><td>Expression</td><td><code>Encounter.class</code></td></tr><tr><td>Multiples</td><td>The parameter can repeat (and) and can have repeating values (or)</td></tr></table></div>"},"url":"http://www.hl7korea.or.kr/fhir/krcore/SearchParameter/krcore-sp-encounter-class","version":"1.0.1","name":"KRCoreSearchParameterEncounterClass","derivedFrom":"http://hl7.org/fhir/SearchParameter/Encounter-class","status":"active","experimental":false,"date":"2023-06-30T13:42:49+09:00","publisher":"HL7 Korea","contact":[{"name":"HL7 Korea","telecom":[{"system":"url","value":"http://www.hl7korea.or.kr/"},{"system":"email","value":"contact@healthall.co.kr"}]},{"name":"HealthAll Inc.","telecom":[{"system":"email","value":"contact@healthall.co.kr","use":"work"}]}],"description":"진료 구분","jurisdiction":[{"coding":[{"system":"urn:iso:std:iso:3166","code":"KR","display":"Korea, Republic of"}]}],"code":"class","base":["Encounter"],"type":"token","expression":"Encounter.class","multipleOr":true,"_multipleOr":{"extension":[{"url":"http://hl7.org/fhir/StructureDefinition/capabilitystatement-expectation","valueCode":"MAY"}]},"multipleAnd":true,"_multipleAnd":{"extension":[{"url":"http://hl7.org/fhir/StructureDefinition/capabilitystatement-expectation","valueCode":"MAY"}]}}